SSG/ssg.py
SSG/tests/ssgTests.py
SSG/tests/testFiles/test1.txt
SSG/tests/testFiles/test2.md
SSG/tests/testFiles/testEmp.txt
SSG/utils/help.py
SSG/utils/input.py
SSG/utils/version.py
pdrozd_ssg-1.0.15.dist-info/entry_points.txt
pdrozd_ssg-1.0.15.dist-info/METADATA
pdrozd_ssg-1.0.15.dist-info/LICENSE
pdrozd_ssg-1.0.15.dist-info/WHEEL
pdrozd_ssg-1.0.15.dist-info/RECORD
