Metadata-Version: 2.1
Name: pdrozd-ssg
Version: 1.0.15
Summary: P-DR0ZD-SSG
License: GNU
Author: P-DR0ZD
Author-email: 60482468+P-DR0ZD@users.noreply.github.com
Requires-Python: >=3.10,<4.0
Classifier: License :: Other/Proprietary License
Classifier: Programming Language :: Python :: 3
Classifier: Programming Language :: Python :: 3.10
Classifier: Programming Language :: Python :: 3.11
Requires-Dist: Markdown (>=3.4.1,<4.0.0)
Requires-Dist: Poetry (>=1.2.2,<2.0.0)
Requires-Dist: black (>=22.10.0,<23.0.0)
Requires-Dist: flake8 (>=5.0.4,<6.0.0)
